ambition_django_cachebuster-0.3.dist-info/DESCRIPTION.rst
ambition_django_cachebuster-0.3.dist-info/METADATA
ambition_django_cachebuster-0.3.dist-info/metadata.json
ambition_django_cachebuster-0.3.dist-info/pbr.json
ambition_django_cachebuster-0.3.dist-info/RECORD
ambition_django_cachebuster-0.3.dist-info/top_level.txt
ambition_django_cachebuster-0.3.dist-info/WHEEL
cachebuster/__init__.py
cachebuster/context_processors.py
cachebuster/models.py
cachebuster/tests.py
cachebuster/views.py
cachebuster/detectors/__init__.py
cachebuster/detectors/git.py
cachebuster/templatetags/__init__.py
cachebuster/templatetags/cachebuster.py
