Metadata-Version: 2.0
Name: ambition-django-cachebuster
Version: 0.3
Summary: Django 1.3, Python 2.7/3.5 ready cache busting app
Home-page: http://github.com/ambitioninc/django-cachebuster
Author: James Addison
Author-email: code@scottisheyes.com
License: BSD
Platform: UNKNOWN
Classifier: Development Status :: 3 - Alpha
Classifier: Intended Audience :: Developers
Classifier: License :: OSI Approved :: BSD License
Classifier: Topic :: Internet :: WWW/HTTP :: WSGI
Classifier: Framework :: Django
